sparklestock/Stock.py
sparklestock/__init__.py
sparklestock/__version__.py
sparklestock-0.0.1.1.dist-info/METADATA
sparklestock-0.0.1.1.dist-info/WHEEL
sparklestock-0.0.1.1.dist-info/top_level.txt
sparklestock-0.0.1.1.dist-info/RECORD
