Metadata-Version: 2.1
Name: sparklestock
Version: 0.0.1.1
Summary: sparkle stock package
Home-page: https://github.com/hiseyong
Author: Seyong Ahn
Author-email: hiseyong1008@gmail.com
Classifier: Programming Language :: Python :: 3
Classifier: License :: OSI Approved :: MIT License
Classifier: Operating System :: OS Independent
Requires-Python: >=3
Requires-Dist: requests
